setup.cfg
setup.py
pyokcoin/__init__.py
pyokcoin/api.py
pyokcoin/client.py
pyokcoin.egg-info/PKG-INFO
pyokcoin.egg-info/SOURCES.txt
pyokcoin.egg-info/dependency_links.txt
pyokcoin.egg-info/requires.txt
pyokcoin.egg-info/top_level.txt
tests/__init__.py
tests/test_okcoin.py