Metadata-Version: 1.1
Name: pyokcoin
Version: 0.0.2
Summary: okcoin simple restful api
Home-page: https://github.com/chiangqiqi/pyokcoin
Author: Alex Jiang
Author-email: chiangqiqi@gmail.com
License: UNKNOWN
Download-URL: https://github.com/chiangqiqi/pyokcoin/archive/0.0.2.tar.gz
Platform: UNKNOWN
